JinuTest/test1.py
JinuTest/test2.py
JinuTest-0.0.0.2.dist-info/METADATA
JinuTest-0.0.0.2.dist-info/WHEEL
JinuTest-0.0.0.2.dist-info/top_level.txt
JinuTest-0.0.0.2.dist-info/RECORD
