Metadata-Version: 2.1
Name: JinuTest
Version: 0.0.0.2
Summary: My First Test Package
Home-page: https://naver.com...
Author: BJWPY
Author-email: beak1011@naver.com
License: MIT
Platform: UNKNOWN
Requires-Python: >=3
